npline/__init__.py
npline/core/__init__.py
npline/core/np_line_shared.py
npline-2024.1.1.dist-info/LICENSE
npline-2024.1.1.dist-info/METADATA
npline-2024.1.1.dist-info/WHEEL
npline-2024.1.1.dist-info/top_level.txt
npline-2024.1.1.dist-info/RECORD
